quilt3distribute/__init__.py
quilt3distribute/dataset.py
quilt3distribute/documentation.py
quilt3distribute/file_utils.py
quilt3distribute/validation.py
quilt3distribute/bin/__init__.py
quilt3distribute/bin/quilt3_distribute_dataset.py
quilt3distribute-0.1.4.dist-info/LICENSE
quilt3distribute-0.1.4.dist-info/METADATA
quilt3distribute-0.1.4.dist-info/WHEEL
quilt3distribute-0.1.4.dist-info/entry_points.txt
quilt3distribute-0.1.4.dist-info/top_level.txt
quilt3distribute-0.1.4.dist-info/RECORD
